power1d/__init__.py
power1d/_assert.py
power1d/_base.py
power1d/_plot.py
power1d/data.py
power1d/geom.py
power1d/io.py
power1d/models.py
power1d/noise.py
power1d/prob.py
power1d/random.py
power1d/results.py
power1d/roi.py
power1d/stats.py
power1d/data/weather/README.txt
power1d/data/weather/daily.m
power1d/data/weather/daily.mat
power1d/data/weather/daily.npz
power1d-0.1.15.dist-info/LICENSE.txt
power1d-0.1.15.dist-info/METADATA
power1d-0.1.15.dist-info/WHEEL
power1d-0.1.15.dist-info/top_level.txt
power1d-0.1.15.dist-info/RECORD
