Metadata-Version: 2.1
Name: power1d
Version: 0.1.15
Summary: Numerical Power Estimates for One-Dimensional Continua
Author-email: Todd Pataky <0todd0@gmail.com>
Project-URL: Homepage, https://www.spm1d.org/power1d
Project-URL: Source, https://github.com/0todd0000/power1d
Project-URL: Bug Reports, https://github.com/0todd0000/power1d/issues
Keywords: statistics,probability,hypothesis testing,functional data analysis,time series analysis,continuum data analysis
Classifier: Development Status :: 4 - Beta
Classifier: License :: OSI Approved :: GNU General Public License v3 (GPLv3)
Classifier: Topic :: Scientific/Engineering
Classifier: Programming Language :: Python :: 3.9
Requires-Python: >=3.7
License-File: LICENSE.txt
Requires-Dist: numpy
Requires-Dist: scipy
Requires-Dist: matplotlib
